setup.py
gevent_subprocess/__init__.py
gevent_subprocess/gevent_subprocess.py
gevent_subprocess.egg-info/PKG-INFO
gevent_subprocess.egg-info/SOURCES.txt
gevent_subprocess.egg-info/dependency_links.txt
gevent_subprocess.egg-info/not-zip-safe
gevent_subprocess.egg-info/requires.txt
gevent_subprocess.egg-info/top_level.txt
test/test_communicate.py
test/test_helpers.py
test/test_pipe.py
test/test_wait.py